<?xml version="1.0" encoding="UTF-8"?>
<PeakList>
  <PeakList1D>
    <PeakList1DHeader creator="NMR Superuser" date="2019-06-25T15:21:32.184+01:00" expNo="1" name="EMKM-04P1_2" owner="" procNo="1" source="C:/Data/MSc/Macnab">
      <PeakPickDetails>F1=17.000170ppm, F2=-3.000170ppm, MI=0.10cm, MAXI=10000.00cm, PC=1.000
      </PeakPickDetails>
    </PeakList1DHeader>
    <Peak1D F1="8.062008" intensity="1.007771e+001" type="0"/>
    <Peak1D F1="8.044063" intensity="1.108246e+001" type="0"/>
    <Peak1D F1="8.040644" intensity="8.413307e+000" type="0"/>
    <Peak1D F1="8.018614" intensity="1.331123e-001" type="0"/>
    <Peak1D F1="7.999829" intensity="4.629745e-001" type="0"/>
    <Peak1D F1="7.978348" intensity="1.153805e+000" type="0"/>
    <Peak1D F1="7.959211" intensity="9.118785e-001" type="0"/>
    <Peak1D F1="7.955929" intensity="7.116938e-001" type="0"/>
    <Peak1D F1="7.865124" intensity="6.715683e+000" type="0"/>
    <Peak1D F1="7.825782" intensity="8.788433e+000" type="0"/>
    <Peak1D F1="7.775450" intensity="1.288997e-001" type="0"/>
    <Peak1D F1="7.756772" intensity="1.001765e-001" type="0"/>
    <Peak1D F1="7.736853" intensity="1.751160e-001" type="0"/>
    <Peak1D F1="7.690188" intensity="5.955807e+000" type="0"/>
    <Peak1D F1="7.681260" intensity="7.735562e+000" type="0"/>
    <Peak1D F1="7.671687" intensity="7.722351e+000" type="0"/>
    <Peak1D F1="7.666499" intensity="6.917279e+000" type="0"/>
    <Peak1D F1="7.657587" intensity="1.216293e+000" type="0"/>
    <Peak1D F1="7.638083" intensity="1.920415e+000" type="0"/>
    <Peak1D F1="7.619776" intensity="5.613911e+000" type="0"/>
    <Peak1D F1="7.601383" intensity="4.457012e+000" type="0"/>
    <Peak1D F1="7.584987" intensity="1.115984e+001" type="0"/>
    <Peak1D F1="7.572039" intensity="9.824237e-001" type="0"/>
    <Peak1D F1="7.556756" intensity="8.525407e+000" type="0"/>
    <Peak1D F1="7.545569" intensity="9.792223e+000" type="0"/>
    <Peak1D F1="7.537466" intensity="1.150677e+001" type="0"/>
    <Peak1D F1="7.519404" intensity="4.577895e+000" type="0"/>
    <Peak1D F1="7.492527" intensity="6.856596e-001" type="0"/>
    <Peak1D F1="7.485553" intensity="1.164681e+000" type="0"/>
    <Peak1D F1="7.465292" intensity="4.247688e+000" type="0"/>
    <Peak1D F1="7.458925" intensity="1.098560e+001" type="0"/>
    <Peak1D F1="7.448855" intensity="1.500000e+001" type="0"/>
    <Peak1D F1="7.442665" intensity="1.414969e+001" type="0"/>
    <Peak1D F1="7.432868" intensity="1.955021e+000" type="0"/>
    <Peak1D F1="7.426651" intensity="1.613627e+000" type="0"/>
    <Peak1D F1="7.414824" intensity="9.867713e-001" type="0"/>
    <Peak1D F1="7.396907" intensity="9.661684e-001" type="0"/>
    <Peak1D F1="7.377804" intensity="4.153236e-001" type="0"/>
    <Peak1D F1="7.353281" intensity="1.333322e-001" type="0"/>
    <Peak1D F1="7.340889" intensity="4.705852e-001" type="0"/>
    <Peak1D F1="7.324127" intensity="7.720083e-001" type="0"/>
    <Peak1D F1="7.315239" intensity="6.447672e-001" type="0"/>
    <Peak1D F1="7.305495" intensity="2.984172e-001" type="0"/>
    <Peak1D F1="7.296794" intensity="2.691379e-001" type="0"/>
    <Peak1D F1="7.285264" intensity="5.496039e+000" type="0"/>
    <Peak1D F1="7.262209" intensity="2.465536e-001" type="0"/>
    <Peak1D F1="7.252121" intensity="2.716244e-001" type="0"/>
    <Peak1D F1="7.245914" intensity="2.679203e-001" type="0"/>
    <Peak1D F1="7.058727" intensity="1.127716e-001" type="0"/>
    <Peak1D F1="7.026660" intensity="1.318707e-001" type="0"/>
    <Peak1D F1="6.963939" intensity="2.488324e-001" type="0"/>
    <Peak1D F1="6.958153" intensity="1.011678e-001" type="0"/>
    <Peak1D F1="6.941825" intensity="5.032482e-001" type="0"/>
    <Peak1D F1="6.926562" intensity="1.180527e-001" type="0"/>
    <Peak1D F1="6.920615" intensity="3.560701e-001" type="0"/>
    <Peak1D F1="6.831108" intensity="4.015790e-001" type="0"/>
    <Peak1D F1="6.820335" intensity="4.003196e-001" type="0"/>
    <Peak1D F1="6.814353" intensity="2.050092e-001" type="0"/>
    <Peak1D F1="6.808440" intensity="2.813609e-001" type="0"/>
    <Peak1D F1="6.803565" intensity="1.209224e-001" type="0"/>
    <Peak1D F1="6.797808" intensity="2.659410e-001" type="0"/>
    <Peak1D F1="6.663798" intensity="1.559982e-001" type="0"/>
    <Peak1D F1="6.631679" intensity="1.328484e-001" type="0"/>
    <Peak1D F1="5.058023" intensity="1.691924e-001" type="0"/>
    <Peak1D F1="5.044260" intensity="1.696952e-001" type="0"/>
    <Peak1D F1="4.927910" intensity="3.157617e-001" type="0"/>
    <Peak1D F1="4.917033" intensity="3.324465e-001" type="0"/>
    <Peak1D F1="4.906934" intensity="3.385886e-001" type="0"/>
    <Peak1D F1="4.896082" intensity="3.233549e-001" type="0"/>
    <Peak1D F1="3.866685" intensity="1.034818e-001" type="0"/>
    <Peak1D F1="3.849014" intensity="1.046063e-001" type="0"/>
    <Peak1D F1="3.670720" intensity="1.256752e-001" type="0"/>
    <Peak1D F1="3.653502" intensity="4.746858e-001" type="0"/>
    <Peak1D F1="3.646601" intensity="1.190874e-001" type="0"/>
    <Peak1D F1="3.632558" intensity="3.971424e-001" type="0"/>
    <Peak1D F1="3.612442" intensity="4.605773e-001" type="0"/>
    <Peak1D F1="3.591324" intensity="4.294173e-001" type="0"/>
    <Peak1D F1="3.533419" intensity="7.614112e-001" type="0"/>
    <Peak1D F1="3.515860" intensity="2.263349e+000" type="0"/>
    <Peak1D F1="3.498309" intensity="2.284183e+000" type="0"/>
    <Peak1D F1="3.480778" intensity="7.782086e-001" type="0"/>
    <Peak1D F1="3.265233" intensity="5.058473e+000" type="0"/>
    <Peak1D F1="3.135842" intensity="4.414942e-001" type="0"/>
    <Peak1D F1="3.124947" intensity="4.378032e-001" type="0"/>
    <Peak1D F1="3.094642" intensity="3.839038e-001" type="0"/>
    <Peak1D F1="3.083805" intensity="3.813014e-001" type="0"/>
    <Peak1D F1="2.638350" intensity="1.853218e+000" type="0"/>
    <Peak1D F1="2.070441" intensity="1.675368e-001" type="0"/>
    <Peak1D F1="1.646511" intensity="1.834784e+000" type="0"/>
    <Peak1D F1="1.605120" intensity="2.635209e-001" type="0"/>
    <Peak1D F1="1.584987" intensity="1.764152e-001" type="0"/>
    <Peak1D F1="1.567197" intensity="1.423160e-001" type="0"/>
    <Peak1D F1="1.548004" intensity="1.076558e-001" type="0"/>
    <Peak1D F1="1.537960" intensity="1.500018e-001" type="0"/>
    <Peak1D F1="1.408886" intensity="8.549611e-001" type="0"/>
    <Peak1D F1="1.395150" intensity="8.048289e-001" type="0"/>
    <Peak1D F1="1.296257" intensity="4.527699e-001" type="0"/>
    <Peak1D F1="1.284805" intensity="3.824963e-001" type="0"/>
    <Peak1D F1="1.278643" intensity="8.664274e-001" type="0"/>
    <Peak1D F1="1.271143" intensity="3.800401e-001" type="0"/>
    <Peak1D F1="1.260785" intensity="6.033633e-001" type="0"/>
    <Peak1D F1="1.253362" intensity="2.613437e+000" type="0"/>
    <Peak1D F1="1.242954" intensity="1.520433e+000" type="0"/>
    <Peak1D F1="1.235820" intensity="4.818715e+000" type="0"/>
    <Peak1D F1="1.218248" intensity="2.365814e+000" type="0"/>
    <Peak1D F1="1.193136" intensity="6.889643e-001" type="0"/>
    <Peak1D F1="1.168672" intensity="1.768468e-001" type="0"/>
    <Peak1D F1="0.971912" intensity="1.651904e-001" type="0"/>
    <Peak1D F1="0.953780" intensity="3.247369e-001" type="0"/>
    <Peak1D F1="0.940916" intensity="3.973993e-001" type="0"/>
    <Peak1D F1="0.935727" intensity="1.917757e-001" type="0"/>
    <Peak1D F1="0.923691" intensity="3.348692e-001" type="0"/>
    <Peak1D F1="0.909650" intensity="1.893007e-001" type="0"/>
  </PeakList1D>
</PeakList>
